cachebrowser/__init__.py
cachebrowser/basescrambler.py
cachebrowser/bootstrap.py
cachebrowser/cli.py
cachebrowser/ipc.py
cachebrowser/log.py
cachebrowser/main.py
cachebrowser/models.py
cachebrowser/proxy.py
cachebrowser/resolver.py
cachebrowser/scrambler.py
cachebrowser/util.py
cachebrowser/api/__init__.py
cachebrowser/api/core.py
cachebrowser/api/routes.py
cachebrowser/api/handlers/__init__.py
cachebrowser/api/handlers/bootstrap.py
cachebrowser/api/handlers/process.py
cachebrowser/data/ad-domains
cachebrowser/data/blacklist
cachebrowser/data/cachebrowser.db
cachebrowser/data/config.yaml
cachebrowser/data/decoy.json
cachebrowser/data/decoy.json.bak
cachebrowser/data/decoy.json.old
cachebrowser/data/decoys.json
cachebrowser/data/local_bootstrap.yaml
cachebrowser/data/local_bootstrap.yaml.old
cachebrowser/data/sites
cachebrowser/data/mitmproxy/onboarding/__init__.py
cachebrowser/data/mitmproxy/onboarding/app.py
cachebrowser/data/mitmproxy/onboarding/static/bootstrap.min.css
cachebrowser/data/mitmproxy/onboarding/static/mitmproxy.css
cachebrowser/data/mitmproxy/onboarding/static/fontawesome/css/font-awesome.css
cachebrowser/data/mitmproxy/onboarding/static/fontawesome/css/font-awesome.min.css
cachebrowser/data/mitmproxy/onboarding/static/fontawesome/fonts/FontAwesome.otf
cachebrowser/data/mitmproxy/onboarding/static/fontawesome/fonts/fontawesome-webfont.eot
cachebrowser/data/mitmproxy/onboarding/static/fontawesome/fonts/fontawesome-webfont.svg
cachebrowser/data/mitmproxy/onboarding/static/fontawesome/fonts/fontawesome-webfont.ttf
cachebrowser/data/mitmproxy/onboarding/static/fontawesome/fonts/fontawesome-webfont.woff
cachebrowser/data/mitmproxy/onboarding/templates/frame.html
cachebrowser/data/mitmproxy/onboarding/templates/index.html
cachebrowser/data/mitmproxy/onboarding/templates/layout.html
cachebrowser/pipes/__init__.py
cachebrowser/pipes/base.py
cachebrowser/pipes/publisher.py
cachebrowser/pipes/resolver.py
cachebrowser-0.1.1.dist-info/DESCRIPTION.rst
cachebrowser-0.1.1.dist-info/METADATA
cachebrowser-0.1.1.dist-info/RECORD
cachebrowser-0.1.1.dist-info/WHEEL
cachebrowser-0.1.1.dist-info/entry_points.txt
cachebrowser-0.1.1.dist-info/metadata.json
cachebrowser-0.1.1.dist-info/top_level.txt
